jweather_mcp_server/__init__.py
jweather_mcp_server/__main__.py
jweather_mcp_server/server.py
jweather_mcp_server-0.1.0.dist-info/METADATA
jweather_mcp_server-0.1.0.dist-info/WHEEL
jweather_mcp_server-0.1.0.dist-info/entry_points.txt
jweather_mcp_server-0.1.0.dist-info/RECORD
