Metadata-Version: 2.4
Name: jweather-mcp-server
Version: 0.1.0
Summary: 一个提供全国天气预报查询功能的模型上下文协议（Model Context Protocol）服务器。该服务器使大型语言模型（LLMs）能够获取全国城市、地区的天气预报情况。
Author-email: juhemcp <dev@juheapi.com>
Requires-Python: >=3.10
Requires-Dist: mcp[cli]>=1.4.1
